cnbcfinance/__init__.py
cnbcfinance/__version__.py
cnbcfinance/cnbc.py
cnbcfinance-0.0.4.dist-info/LICENSE
cnbcfinance-0.0.4.dist-info/METADATA
cnbcfinance-0.0.4.dist-info/WHEEL
cnbcfinance-0.0.4.dist-info/top_level.txt
cnbcfinance-0.0.4.dist-info/RECORD
