Metadata-Version: 2.1
Name: cnbcfinance
Version: 0.0.4
Summary: The package fetch stock data from cnbc.
Home-page: https://github.com/dearvn/cnbcfinance
Author: Donald
Author-email: donald.nguyen.it@gmail.com
License: MIT
Project-URL: Bug Tracker, https://github.com/dearvn/cnbcfinance/issues
Platform: UNKNOWN
Classifier: License :: OSI Approved :: MIT License
Classifier: Programming Language :: Python
Classifier: Programming Language :: Python :: 3
Classifier: Programming Language :: Python :: 3.6
Classifier: Programming Language :: Python :: Implementation :: CPython
Classifier: Programming Language :: Python :: Implementation :: PyPy
Requires-Python: >=3.6.0
License-File: LICENSE
Requires-Dist: requests
Requires-Dist: pytz
Requires-Dist: pandas
